pymata_cpx/__init__.py
pymata_cpx/constants.py
pymata_cpx/pymata_cpx.py
pymata_cpx/pymata_cpx_command_handler.py
pymata_cpx/pymata_cpx_serial.py
pymata_cpx-1.0.dist-info/METADATA
pymata_cpx-1.0.dist-info/WHEEL
pymata_cpx-1.0.dist-info/top_level.txt
pymata_cpx-1.0.dist-info/RECORD
