Metadata-Version: 2.1
Name: pymata-cpx
Version: 1.0
Summary: A Python API For The Circuit Playground Express
Home-page: https://mryslab.github.io/pymata-cpx/
Author: Alan Yorinks
Author-email: MisterYsLab@gmail.com
License: GNU Affero General Public License v3 or later (AGPLv3+)
Download-URL: https://github.com/MrYsLab/pymata-cpx
Keywords: Circuit Playground Express,Python
Platform: UNKNOWN
Classifier: Development Status :: 5 - Production/Stable
Classifier: Environment :: Other Environment
Classifier: Intended Audience :: Developers
Classifier: Intended Audience :: Education
Classifier: License :: OSI Approved :: GNU Affero General Public License v3 or later (AGPLv3+)
Classifier: Operating System :: OS Independent
Classifier: Programming Language :: Python :: 3 :: Only
Classifier: Topic :: Utilities
Classifier: Topic :: Education
Requires-Dist: pyserial
